Workbook
Name Slicer_Category: #N/A
Name Slicer_City: #N/A
Name Slicer_month_name: #N/A
Name Slicer_Payment_Mode: #N/A

Sheet Raw_data 
A1: Order_ID | B1: Order_Date | C1: Customer | D1: City | E1: Product | F1: Category | G1: Quantity | H1: Unit_Price | I1: Discount_% | J1: Sales_Person | K1: Payment_Mode | L1: Total_Sales | M1: sales status | N1: status | O1: bonus status | P1: year | Q1: month no | R1: month name | S1: quarter | T1: day name | U1: week no
A2: 1076 | B2: 46176 | C2: Amit | D2: Ahmedabad | E2: Keyboard | F2: Electronics | G2: 8 | H2: 750 | I2: 5 | J2: Chirag | K2: UPI | L2: =G2*H2*(1-I2/100) -> 5700 | M2: =IF(L2>=20000,"high sales","low sales") -> low sales | N2: =IF(L2>=115000,"Excellent",IF(L2>=12000,"good",IF(L2>=6000,"average","LOW SALES"))) -> LOW SALES | O2: =IF(AND(L2>=9000,D2="SURAT"),"BONUS","NO BONUS") -> NO BONUS | P2: =YEAR(B2) -> 2026 | Q2: =MONTH(B2) -> 6 | R2: =TEXT(B2,"mmmm") -> June | S2: ="Q"&ROUNDUP(MONTH(B2)/3,0) -> Q2 | T2: =TEXT(B2,"dddd") -> Wednesday | U2: =WEEKNUM(B2) -> 23
A3: 1039 | B3: 46028 | C3: Amit | D3: Ahmedabad | E3: Bottle | F3: Accessories | G3: 8 | H3: 1000 | I3: 0 | J3: Chirag | K3: UPI | L3: =G3*H3*(1-I3/100) -> 8000 | M3: =IF(L3>=20000,"high sales","low sales") -> low sales | N3: =IF(L3>=115000,"Excellent",IF(L3>=12000,"good",IF(L3>=6000,"average","LOW SALES"))) -> average | O3: =IF(AND(L3>=9000,D3="SURAT"),"BONUS","NO BONUS") -> NO BONUS | P3: =YEAR(B3) -> 2026 | Q3: =MONTH(B3) -> 1 | R3: =TEXT(B3,"mmmm") -> January | S3: ="Q"&ROUNDUP(MONTH(B3)/3,0) -> Q1 | T3: =TEXT(B3,"dddd") -> Tuesday | U3: =WEEKNUM(B3) -> 2
A4: 1022 | B4: 46157 | C4: Dev | D4: Ahmedabad | E4: Laptop | F4: Electronics | G4: 2 | H4: 500 | I4: 20 | J4: Anil | K4: Cash | L4: =G4*H4*(1-I4/100) -> 800 | M4: =IF(L4>=20000,"high sales","low sales") -> low sales | N4: =IF(L4>=115000,"Excellent",IF(L4>=12000,"good",IF(L4>=6000,"average","LOW SALES"))) -> LOW SALES | O4: =IF(AND(L4>=9000,D4="SURAT"),"BONUS","NO BONUS") -> NO BONUS | P4: =YEAR(B4) -> 2026 | Q4: =MONTH(B4) -> 5 | R4: =TEXT(B4,"mmmm") -> May | S4: ="Q"&ROUNDUP(MONTH(B4)/3,0) -> Q2 | T4: =TEXT(B4,"dddd") -> Friday | U4: =WEEKNUM(B4) -> 20
A5: 1081 | B5: 46129 | C5: Dev | D5: Ahmedabad | E5: Mouse | F5: Electronics | G5: 1 | H5: 1000 | I5: 15 | J5: Anil | K5: Cash | L5: =G5*H5*(1-I5/100) -> 850 | M5: =IF(L5>=20000,"high sales","low sales") -> low sales | N5: =IF(L5>=115000,"Excellent",IF(L5>=12000,"good",IF(L5>=6000,"average","LOW SALES"))) -> LOW SALES | O5: =IF(AND(L5>=9000,D5="SURAT"),"BONUS","NO BONUS") -> NO BONUS | P5: =YEAR(B5) -> 2026 | Q5: =MONTH(B5) -> 4 | R5: =TEXT(B5,"mmmm") -> April | S5: ="Q"&ROUNDUP(MONTH(B5)/3,0) -> Q2 | T5: =TEXT(B5,"dddd") -> Friday | U5: =WEEKNUM(B5) -> 16
A6: 1063 | B6: 46181 | C6: Dev | D6: Ahmedabad | E6: Table | F6: Furniture | G6: 8 | H6: 5000 | I6: 10 | J6: Esha | K6: Net Banking | L6: =G6*H6*(1-I6/100) -> 36000 | M6: =IF(L6>=20000,"high sales","low sales") -> high sales | N6: =IF(L6>=115000,"Excellent",IF(L6>=12000,"good",IF(L6>=6000,"average","LOW SALES"))) -> good | O6: =IF(AND(L6>=9000,D6="SURAT"),"BONUS","NO BONUS") -> NO BONUS | P6: =YEAR(B6) -> 2026 | Q6: =MONTH(B6) -> 6 | R6: =TEXT(B6,"mmmm") -> June | S6: ="Q"&ROUNDUP(MONTH(B6)/3,0) -> Q2 | T6: =TEXT(B6,"dddd") -> Monday | U6: =WEEKNUM(B6) -> 24
A7: 1015 | B7: 46144 | C7: Karan | D7: Ahmedabad | E7: Chair | F7: Furniture | G7: 7 | H7: 250 | I7: 20 | J7: Bhavna | K7: Cash | L7: =G7*H7*(1-I7/100) -> 1400 | M7: =IF(L7>=20000,"high sales","low sales") -> low sales | N7: =IF(L7>=115000,"Excellent",IF(L7>=12000,"good",IF(L7>=6000,"average","LOW SALES"))) -> LOW SALES | O7: =IF(AND(L7>=9000,D7="SURAT"),"BONUS","NO BONUS") -> NO BONUS | P7: =YEAR(B7) -> 2026 | Q7: =MONTH(B7) -> 5 | R7: =TEXT(B7,"mmmm") -> May | S7: ="Q"&ROUNDUP(MONTH(B7)/3,0) -> Q2 | T7: =TEXT(B7,"dddd") -> Saturday | U7: =WEEKNUM(B7) -> 18
A8: 1073 | B8: 46029 | C8: Karan | D8: Ahmedabad | E8: Bag | F8: Accessories | G8: 3 | H8: 2500 | I8: 15 | J8: Esha | K8: UPI | L8: =G8*H8*(1-I8/100) -> 6375 | M8: =IF(L8>=20000,"high sales","low sales") -> low sales | N8: =IF(L8>=115000,"Excellent",IF(L8>=12000,"good",IF(L8>=6000,"average","LOW SALES"))) -> average | O8: =IF(AND(L8>=9000,D8="SURAT"),"BONUS","NO BONUS") -> NO BONUS | P8: =YEAR(B8) -> 2026 | Q8: =MONTH(B8) -> 1 | R8: =TEXT(B8,"mmmm") -> January | S8: ="Q"&ROUNDUP(MONTH(B8)/3,0) -> Q1 | T8: =TEXT(B8,"dddd") -> Wednesday | U8: =WEEKNUM(B8) -> 2
A9: 1037 | B9: 46098 | C9: Neha | D9: Ahmedabad | E9: Keyboard | F9: Electronics | G9: 8 | H9: 1500 | I9: 10 | J9: Anil | K9: Card | L9: =G9*H9*(1-I9/100) -> 10800 | M9: =IF(L9>=20000,"high sales","low sales") -> low sales | N9: =IF(L9>=115000,"Excellent",IF(L9>=12000,"good",IF(L9>=6000,"average","LOW SALES"))) -> average | O9: =IF(AND(L9>=9000,D9="SURAT"),"BONUS","NO BONUS") -> NO BONUS | P9: =YEAR(B9) -> 2026 | Q9: =MONTH(B9) -> 3 | R9: =TEXT(B9,"mmmm") -> March | S9: ="Q"&ROUNDUP(MONTH(B9)/3,0) -> Q1 | T9: =TEXT(B9,"dddd") -> Tuesday | U9: =WEEKNUM(B9) -> 12
A10: 1062 | B10: 46120 | C10: Neha | D10: Ahmedabad | E10: Table | F10: Furniture | G10: 10 | H10: 12000 | I10: 5 | J10: Chirag | K10: Card | L10: =G10*H10*(1-I10/100) -> 114000 | M10: =IF(L10>=20000,"high sales","low sales") -> high sales | N10: =IF(L10>=115000,"Excellent",IF(L10>=12000,"good",IF(L10>=6000,"average","LOW SALES"))) -> good | O10: =IF(AND(L10>=9000,D10="SURAT"),"BONUS","NO BONUS") -> NO BONUS | P10: =YEAR(B10) -> 2026 | Q10: =MONTH(B10) -> 4 | R10: =TEXT(B10,"mmmm") -> April | S10: ="Q"&ROUNDUP(MONTH(B10)/3,0) -> Q2 | T10: =TEXT(B10,"dddd") -> Wednesday | U10: =WEEKNUM(B10) -> 15
A11: 1027 | B11: 46081 | C11: Pooja | D11: Ahmedabad | E11: Bottle | F11: Accessories | G11: 2 | H11: 500 | I11: 5 | J11: Deep | K11: Card | L11: =G11*H11*(1-I11/100) -> 950 | M11: =IF(L11>=20000,"high sales","low sales") -> low sales | N11: =IF(L11>=115000,"Excellent",IF(L11>=12000,"good",IF(L11>=6000,"average","LOW SALES"))) -> LOW SALES | O11: =IF(AND(L11>=9000,D11="SURAT"),"BONUS","NO BONUS") -> NO BONUS | P11: =YEAR(B11) -> 2026 | Q11: =MONTH(B11) -> 2 | R11: =TEXT(B11,"mmmm") -> February | S11: ="Q"&ROUNDUP(MONTH(B11)/3,0) -> Q1 | T11: =TEXT(B11,"dddd") -> Saturday | U11: =WEEKNUM(B11) -> 9
A12: 1083 | B12: 46162 | C12: Pooja | D12: Ahmedabad | E12: Keyboard | F12: Electronics | G12: 5 | H12: 250 | I12: 15 | J12: Anil | K12: Card | L12: =G12*H12*(1-I12/100) -> 1062.5 | M12: =IF(L12>=20000,"high sales","low sales") -> low sales | N12: =IF(L12>=115000,"Excellent",IF(L12>=12000,"good",IF(L12>=6000,"average","LOW SALES"))) -> LOW SALES | O12: =IF(AND(L12>=9000,D12="SURAT"),"BONUS","NO BONUS") -> NO BONUS | P12: =YEAR(B12) -> 2026 | Q12: =MONTH(B12) -> 5 | R12: =TEXT(B12,"mmmm") -> May | S12: ="Q"&ROUNDUP(MONTH(B12)/3,0) -> Q2 | T12: =TEXT(B12,"dddd") -> Wednesday | U12: =WEEKNUM(B12) -> 21
A13: 1008 | B13: 46058 | C13: Pooja | D13: Ahmedabad | E13: Keyboard | F13: Electronics | G13: 7 | H13: 250 | I13: 20 | J13: Deep | K13: UPI | L13: =G13*H13*(1-I13/100) -> 1400 | M13: =IF(L13>=20000,"high sales","low sales") -> low sales | N13: =IF(L13>=115000,"Excellent",IF(L13>=12000,"good",IF(L13>=6000,"average","LOW SALES"))) -> LOW SALES | O13: =IF(AND(L13>=9000,D13="SURAT"),"BONUS","NO BONUS") -> NO BONUS | P13: =YEAR(B13) -> 2026 | Q13: =MONTH(B13) -> 2 | R13: =TEXT(B13,"mmmm") -> February | S13: ="Q"&ROUNDUP(MONTH(B13)/3,0) -> Q1 | T13: =TEXT(B13,"dddd") -> Thursday | U13: =WEEKNUM(B13) -> 6
... A101: 1049 | B101: 46106 | C101: Sanjay | D101: Vadodara | E101: Bag | F101: Accessories | G101: 8 | H101: 750 | I101: 15 | J101: Chirag | K101: Cash | L101: =G101*H101*(1-I101/100) -> 5100 | M101: =IF(L101>=20000,"high sales","low sales") -> low sales | N101: =IF(L101>=115000,"Excellent",IF(L101>=12000,"good",IF(L101>=6000,"average","LOW SALES"))) -> LOW SALES | O101: =IF(AND(L101>=9000,D101="SURAT"),"BONUS","NO BONUS") -> NO BONUS | P101: =YEAR(B101) -> 2026 | Q101: =MONTH(B101) -> 3 | R101: =TEXT(B101,"mmmm") -> March | S101: ="Q"&ROUNDUP(MONTH(B101)/3,0) -> Q1 | T101: =TEXT(B101,"dddd") -> Wednesday | U101: =WEEKNUM(B101) -> 13

Sheet clean_data 
A1: Project name | B1: Sales Performance Dashboard | D1: Total Rows | E1: =COUNTA('Raw_data '!A2:A101) -> 100
A2: Dataset name | B2: Retail Sales Dataset | D2: Total Column | E2: =COLUMNS([1]Raw_data!A:O) -> 15
A3: Prepared byy | B3: Dev | D3: Total sales | E3: =SUM('Raw_data '!L2:L101) -> 1713800
A4: version | B4: 1 | D4: Total orders | E4: =COUNTA('Raw_data '!A:A)-1 -> 100
A5: Last updated | B5: 46273 | D5: unique Customer | E5: 10
A6: status | B6: In progress | D6: unique City | E6: 5
A9: check | B9: status | D9: column Name | E9: blank count
A10: Total Rows Count | B10: pass | D10: order id | E10: =COUNTBLANK('Raw_data '!C2:C101) -> 0
A11: Total Columns Count | B11: pass | D11: order Date | E11: =COUNTBLANK('Raw_data '!B2:B101) -> 0
A12: Duplicate Check | B12: pass | D12: customer | E12: =COUNTBLANK('Raw_data '!C2:C101) -> 0
A13: Blank Value Check | B13: pass | D13: city | E13: =COUNTBLANK('Raw_data '!D2:D101) -> 0
A14: Date Format Check | B14: pass | D14: product | E14: =COUNTBLANK('Raw_data '!E2:E101) -> 0
A15: Data Type Check | B15: pass | D15: category | E15: =COUNTBLANK('Raw_data '!F2:F101) -> 0
A16: Invalid Value Check | B16: pass | D16: quantity | E16: =COUNTBLANK('Raw_data '!G2:G101) -> 0
A17: Helper Columns Added | B17: pass | D17: unit price | E17: =COUNTBLANK('Raw_data '!H2:H101) -> 0
A18: Final Validation | B18: =IF(AND(B10="pass",B11="pass",B12="pass",B13="pass",B14="pass",B15="pass",B16="pass"),"PASS","FAIL") -> PASS | D18: discount % | E18: =COUNTBLANK('Raw_data '!I2:I101) -> 0
D19: sales person | E19: =COUNTBLANK('Raw_data '!J2:J101) -> 0
D20: payment mode | E20: =COUNTBLANK('Raw_data '!K2:K101) -> 0
D21: total sales | E21: =COUNTBLANK('Raw_data '!L2:L101) -> 0
A23: Dataset Ready | B23: =IF(B18="PASS","YES","NO") -> YES

Sheet Analysis
A1: Sales Performance Analysis
H2: Helper KPI
A3: KPI Cards | H3: Total Categories | I3: =COUNTA(A11:A13) -> 3
A4: Sum of Total_Sales | B4: Sum of Quantity | C4: Count of Order_ID | D4: Count of Customer
A5: 1713800 | B5: 586 | C5: 100 | D5: 100
A9: Sales by Category | D9: Payment mode
A10: Row Labels | B10: Sum of Total_Sales | D10: Row Labels | E10: Sum of Total_Sales | J10: Row Labels | K10: Count of Customer
A11: Accessories | B11: 339725 | D11: Card | E11: 393400 | J11: Amit | K11: 6
A12: Electronics | B12: 652562.5 | D12: Cash | E12: 516075 | J12: Dev | K12: 8
A13: Furniture | B13: 721512.5 | D13: Net Banking | E13: 312987.5 | J13: Karan | K13: 9
A14: Grand Total | B14: 1713800 | D14: UPI | E14: 491337.5 | J14: Neha | K14: 12
D15: Grand Total | E15: 1713800 | J15: Pooja | K15: 15
J16: Priya | K16: 9
J17: Rahul | K17: 16
A18: Sales by city | D18: Month wise sales | J18: Riya | K18: 10
A19: Row Labels | B19: Sum of Total_Sales | D19: Row Labels | E19: Sum of Total_Sales | J19: Sanjay | K19: 9
A20: Ahmedabad | B20: 457462.5 | D20: January | E20: 275075 | J20: Vivek | K20: 6
A21: Navsari | B21: 237137.5 | D21: February | E21: 175312.5 | J21: Grand Total | K21: 100
A22: Rajkot | B22: 359712.5 | D22: March | E22: 238600
A23: Surat | B23: 304825 | D23: April | E23: 441750
A24: Vadodara | B24: 354662.5 | D24: May | E24: 276512.5
A25: Grand Total | B25: 1713800 | D25: June | E25: 306550
D26: Grand Total | E26: 1713800
A28: Sales by sales_person | D28: Sales status
A29: Row Labels | B29: Sum of Total_Sales | D29: Row Labels | E29: Count of Order_ID
A30: Anil | B30: 308612.5 | D30: high sales | E30: 25
A31: Bhavna | B31: 223412.5 | D31: low sales | E31: 75
A32: Chirag | B32: 443287.5 | D32: Grand Total | E32: 100
A33: Deep | B33: 380050
A34: Esha | B34: 358437.5
A35: Grand Total | B35: 1713800 | D35: bonus status
D36: Row Labels | E36: Count of Order_ID
D37: BONUS | E37: 8
D38: NO BONUS | E38: 92
D39: Grand Total | E39: 100

Sheet Dashboard
A1: SALES PERFORMANCE DASHBOARD
A4: Total sales | E4: Total orders | I4: Total Customers | M4: Total qunatity | Q4: Total Cities | U4: Total Categories
A6: =GETPIVOTDATA("Sum of Total_Sales",Analysis!$A$4) -> 1713800 | E6: =GETPIVOTDATA("Count of Order_ID",Analysis!$A$4) -> 100 | I6: ='clean_data '!E5 -> 10 | M6: =GETPIVOTDATA("Sum of Quantity",Analysis!$A$4) -> 586 | Q6: ='clean_data '!E6 -> 5 | U6: =Analysis!I3 -> 3
